{"is_source_file": true, "format": "JavaScript", "description": "This file is the entry point for a React-based frontend application. It imports React, ReactDOM, styling, and the main App component. It initializes the React root and renders the App component within React.StrictMode into the DOM element with id 'root'.", "external_files": ["react", "react-dom/client", "./index.css", "./App"], "external_methods": ["ReactDOM.createRoot", "root.render"], "published": [], "classes": [], "methods": ["ReactDOM.createRoot", "root.render"], "calls": ["ReactDOM.createRoot", "root.render"], "search-terms": ["React", "ReactDOM", "index.js", "front-end entry point", "React.StrictMode"], "state": 2, "file_id": 7, "knowledge_revision": 24, "git_revision": "e31fb2ca325f0d702a86f363f529b782e04d586c", "ctags": [{"_type": "tag", "name": "root", "path": "/home/kavia/workspace/code-generation/star-wars-character-match-and-portrait-creator-94763-94775/character_generator_frontend/src/index.js", "pattern": "/^const root = ReactDOM.createRoot(document.getElementById('root'));$/", "language": "JavaScript", "kind": "constant"}], "hash": "9fc5841375336fc175b49f8767a11383", "format-version": 4, "code-base-name": "character_generator_frontend", "filename": "character_generator_frontend/src/index.js", "revision_history": [{"24": "e31fb2ca325f0d702a86f363f529b782e04d586c"}]}